juftin_scripts/__init__.py
juftin_scripts/__main__.py
juftin_scripts/_base.py
juftin_scripts/_version.py
juftin_scripts/code_browser.css
juftin_scripts/code_browser.py
juftin_scripts/py.typed
juftin_scripts/rotation.py
juftin_scripts-0.4.0.dist-info/LICENSE
juftin_scripts-0.4.0.dist-info/METADATA
juftin_scripts-0.4.0.dist-info/WHEEL
juftin_scripts-0.4.0.dist-info/entry_points.txt
juftin_scripts-0.4.0.dist-info/RECORD
