Metadata-Version: 2.1
Name: juftin-scripts
Version: 0.4.0
Summary: Helpful Python scripts by @juftin
Home-page: https://github.com/juftin/juftin-scripts
License: MIT
Author: Justin Flannery
Author-email: juftin@juftin.com
Requires-Python: >=3.8,<4.0
Classifier: Development Status :: 3 - Alpha
Classifier: License :: OSI Approved :: MIT License
Classifier: Operating System :: OS Independent
Classifier: Programming Language :: Python :: 3
Classifier: Programming Language :: Python :: 3.8
Classifier: Programming Language :: Python :: 3.9
Classifier: Programming Language :: Python :: 3.10
Classifier: Programming Language :: Python :: 3.11
Classifier: Programming Language :: Python :: 3
Classifier: Programming Language :: Python :: 3.10
Classifier: Programming Language :: Python :: 3.7
Classifier: Programming Language :: Python :: 3.8
Classifier: Programming Language :: Python :: 3.9
Provides-Extra: all
Provides-Extra: fsspec
Provides-Extra: parquet
Requires-Dist: adlfs (>=2023.1.0,<2024.0.0) ; extra == "all" or extra == "fsspec"
Requires-Dist: aiohttp (>=3.8.3,<4.0.0) ; extra == "all" or extra == "fsspec"
Requires-Dist: art (>=5.7,<6.0)
Requires-Dist: click (>=8.1.2,<9.0.0)
Requires-Dist: fsspec (>=2023.1.0,<2024.0.0)
Requires-Dist: gcsfs (>=2023.1.0,<2024.0.0) ; extra == "all" or extra == "fsspec"
Requires-Dist: pandas (>=1.5)
Requires-Dist: pyarrow (>=10.0.0,<11.0.0) ; extra == "all" or extra == "parquet"
Requires-Dist: requests (>=2.28.2,<3.0.0) ; extra == "all" or extra == "fsspec"
Requires-Dist: rich (>=13.3.2,<14.0.0)
Requires-Dist: rich-click (>=1.5.2,<2.0.0)
Requires-Dist: rich-pixels (>=2.1.1,<3.0.0)
Requires-Dist: s3fs (>=2023.1.0,<2024.0.0) ; extra == "all" or extra == "fsspec"
Requires-Dist: textual (>=0.15.1,<0.16.0)
Requires-Dist: universal-pathlib (>=0.0.21,<0.0.22)
Project-URL: Changelog, https://github.com/juftin/juftin-scripts/releases
Project-URL: Documentation, https://juftin.github.io/juftin-scripts
Project-URL: Repository, https://github.com/juftin/juftin-scripts
